mshow
