Metadata-Version: 1.0
Name: mshow
Version: 5.1
Summary: Sample Message Showing Library
Home-page: https://github.com/nishantsinghdev/mshow
Author: Nishant Singh
Author-email: nishant@example.com
License: MIT
Platform: UNKNOWN
